Workbook

Sheet 1 Drivers
A1: Pavo Cloud — Model Drivers
A2: Every other tab reads from here. Change a cell and the whole model moves.
A4: Driver | B4: 2026 | C4: 2027 | D4: 2028 | E4: Unit | F4: Basis / source
A5: VOLUME
A6: Provider groups — ending | B6: 110 | C6: 560 | D6: 2240 | E6: Sales plan. A 'group' averages 8 physicians.
A7: Provider groups — average active | B7: 55 | C7: 330 | D7: 1400 | E7: Monthly-weighted; back-loaded ramp within each year.
A8: Physicians per group | B8: 8 | C8: 8 | D8: 8 | E8: Mid-market target segment.
A9: Prior auths per physician per week | B9: 30 | C9: 30 | D9: 30 | E9: Conservative. AMA 2023 survey reports 43–45.
A10: Share of PA volume routed through Pavo | B10: 0.25 | C10: 0.4 | D10: 0.5 | E10: Rises as the encoded rule library widens.
A11: Payer contracts — average active | B11: 11 | C11: 84 | D11: 160 | E11: ~18% of the ~900 payers impacted by CMS-0057-F by 2028.
A13: PRICE
A14: Fee per authorization | B14: 3 | C14: 3 | D14: 3 | E14: 85–92% below the $15–$40 payers spend manually.
A15: Provider subscription | B15: 400 | C15: 400 | D15: 400 | E15: Per group per month.
A16: Payer compliance API | B16: 20000 | C16: 20000 | D16: 20000 | E16: Per payer per year.
A18: ACQUISITION
A19: New provider groups acquired | B19: 110 | C19: 470 | D19: 1750 | E19: Ending count, less prior ending, plus churned replacements.
A20: New payer contracts acquired | B20: 18 | C20: 122 | D20: 80
A21: Provider CAC | B21: 9500 | C21: 7200 | D21: 6000 | E21: Falls 37%: payer contracts open the provider channel.
A22: Payer CAC | B22: 34000 | C22: 27000 | D22: 22000 | E22: Enterprise cycle, 6–12 months.
A23: Provider annual logo churn | B23: 0.08 | C23: 0.06 | D23: 0.05
A24: Payer annual logo churn | B24: 0.02 | C24: 0.02 | D24: 0.02 | E24: Multi-year compliance contracts.
A26: COST OF REVENUE
A27: Cloud infrastructure | B27: 54000 | C27: 198000 | D27: 900000 | E27: Compute, Postgres, object storage, egress, 7-year retention.
A28: Model API (Insure + appeals only) | B28: 11000 | C28: 62000 | D28: 280000 | E28: Zero tokens on the authorization path — see tab 6.
A29: Clinical rule library — FTE | B29: 1.5 | C29: 3.5 | D29: 8 | E29: Informaticists encoding each payer's published criteria.
A30: Clinical rule library — loaded cost/FTE | B30: 126000 | C30: 130000 | D30: 135000
A31: Implementation & onboarding — FTE | B31: 2 | C31: 4 | D31: 12
A32: Implementation — loaded cost/FTE | B32: 112000 | C32: 119000 | D32: 119000
A33: Customer support — FTE | B33: 1 | C33: 2 | D33: 8
A34: Support — loaded cost/FTE | B34: 92000 | C34: 95000 | D34: 98000
A35: Security & compliance | B35: 118000 | C35: 112000 | D35: 290000 | E35: SOC 2 Type II in Year 1, then surveillance + pen testing.
A37: OPERATING EXPENSE
A38: Engineers | B38: 4 | C38: 12 | D38: 26
A39: Loaded cost per engineer | B39: 170000 | C39: 175000 | D39: 180000
A40: General & administrative | B40: 340000 | C40: 1150000 | D40: 3200000 | E40: Finance, legal, HR, facilities, insurance.
A42: Reading this model: every figure on tabs 2–7 is an Excel formula pointing back at this tab. The three revenue targets carried over from the Round 1 narrative ($1.0M / $8.2M / $36.1M) are not typed anywhere — they fall out of the drivers above. Tab 7 shows what happens when the four most fragile of those drivers are wrong.

Sheet 2 Revenue
A1: Revenue Build
A2: Bottom-up from the driver tab. No figure here is typed in.
A4: Line | B4: 2026 | C4: 2027 | D4: 2028 | E4: Price | F4: Note
A5: AUTHORIZATION VOLUME
A6: Prior auths per group per year | B6: ='1 Drivers'!B8*'1 Drivers'!B9*52 | C6: ='1 Drivers'!C8*'1 Drivers'!C9*52 | D6: ='1 Drivers'!D8*'1 Drivers'!D9*52 | E6: 8 physicians × 30/week × 52 weeks
A7: Authorizations routed through Pavo, per group | B7: =B6*'1 Drivers'!B10 | C7: =C6*'1 Drivers'!C10 | D7: =D6*'1 Drivers'!D10
A8: Total authorizations processed | B8: =B7*'1 Drivers'!B7 | C8: =C7*'1 Drivers'!C7 | D8: =D7*'1 Drivers'!D7
A10: REVENUE BY STREAM
A11: Per-authorization fees | B11: =B8*'1 Drivers'!B14 | C11: =C8*'1 Drivers'!C14 | D11: =D8*'1 Drivers'!D14 | E11: $3.00 per authorization
A12: Provider subscriptions | B12: ='1 Drivers'!B7*'1 Drivers'!B15*12 | C12: ='1 Drivers'!C7*'1 Drivers'!C15*12 | D12: ='1 Drivers'!D7*'1 Drivers'!D15*12 | E12: $400/month per group
A13: Payer compliance API | B13: ='1 Drivers'!B11*'1 Drivers'!B16 | C13: ='1 Drivers'!C11*'1 Drivers'!C16 | D13: ='1 Drivers'!D11*'1 Drivers'!D16 | E13: $20,000/year per payer
A14: Total revenue | B14: =SUM(B11:B13) | C14: =SUM(C11:C13) | D14: =SUM(D11:D13)
A15: Year-on-year growth | C15: =C14/B14-1 | D15: =D14/C14-1
A17: MIX
A18: Authorization fees, share of revenue | B18: =B11/B14 | C18: =C11/C14 | D18: =D11/D14
A19: Subscriptions, share of revenue | B19: =B12/B14 | C19: =C12/C14 | D19: =D12/D14
A20: Compliance API, share of revenue | B20: =B13/B14 | C20: =C13/C14 | D20: =D13/D14
A22: The authorization fee is 73% of 2028 revenue, which is why the model's single greatest exposure is provider group count rather than price. Tab 7 quantifies that.

Sheet 3 Cost of Revenue
A1: Cost of Revenue and Gross Margin
A2: The largest line is people encoding payer criteria — not servers.
A4: Line | B4: 2026 | C4: 2027 | D4: 2028 | E4: Driver
A5: Cloud infrastructure | B5: ='1 Drivers'!B27 | C5: ='1 Drivers'!C27 | D5: ='1 Drivers'!D27 | E5: Compute, Postgres, storage, egress, 7-year retention
A6: Model API — Insure parsing, appeal drafting | B6: ='1 Drivers'!B28 | C6: ='1 Drivers'!C28 | D6: ='1 Drivers'!D28 | E6: Not on the authorization path
A7: Clinical rule library | B7: ='1 Drivers'!B29*'1 Drivers'!B30 | C7: ='1 Drivers'!C29*'1 Drivers'!C30 | D7: ='1 Drivers'!D29*'1 Drivers'!D30 | E7: 1.5 → 3.5 → 8.0 FTE informaticists
A8: Implementation & onboarding | B8: ='1 Drivers'!B31*'1 Drivers'!B32 | C8: ='1 Drivers'!C31*'1 Drivers'!C32 | D8: ='1 Drivers'!D31*'1 Drivers'!D32 | E8: 2.0 → 4.0 → 12.0 FTE
A9: Customer support | B9: ='1 Drivers'!B33*'1 Drivers'!B34 | C9: ='1 Drivers'!C33*'1 Drivers'!C34 | D9: ='1 Drivers'!D33*'1 Drivers'!D34 | E9: 1.0 → 2.0 → 8.0 FTE
A10: Security & compliance | B10: ='1 Drivers'!B35 | C10: ='1 Drivers'!C35 | D10: ='1 Drivers'!D35 | E10: SOC 2 Type II, penetration testing, BAA management
A11: Total cost of revenue | B11: =SUM(B5:B10) | C11: =SUM(C5:C10) | D11: =SUM(D5:D10)
A13: Revenue | B13: ='2 Revenue'!B14 | C13: ='2 Revenue'!C14 | D13: ='2 Revenue'!D14
A14: Gross profit | B14: =B13-B11 | C14: =C13-C11 | D14: =D13-D11
A15: Gross margin | B15: =B14/B13 | C15: =C14/C13 | D15: =D14/D13
A17: COST SHARE
A18: People (rule library + implementation + support) | B18: =(B7+B8+B9)/B11 | C18: =(C7+C8+C9)/C11 | D18: =(D7+D8+D9)/D11
A19: Infrastructure + model API | B19: =(B5+B6)/B11 | C19: =(C5+C6)/C11 | D19: =(D5+D6)/D11
A21: Year 1 gross margin of 31% is deliberate and corrects the Round 1 narrative, which implied break-even. Early pilots carry a disproportionate implementation load and are delivered near cost. Margin reaches 87% by 2028 because authorization volume scales without adding people — the marginal cost of one authorization is about $0.00057 (tab 6).

Sheet 4 P&L
A1: Three-Year Profit and Loss
A2: EBITDA-positive during 2028. Peak cumulative burn $5.58M in Q4 2027.
A4: Line | B4: 2026 | C4: 2027 | D4: 2028 | E4: Note
A5: Revenue | B5: ='2 Revenue'!B14 | C5: ='2 Revenue'!C14 | D5: ='2 Revenue'!D14
A6: Cost of revenue | B6: =-'3 Cost of Revenue'!B11 | C6: =-'3 Cost of Revenue'!C11 | D6: =-'3 Cost of Revenue'!D11
A7: Gross profit | B7: =B5+B6 | C7: =C5+C6 | D7: =D5+D6
A8: Gross margin | B8: =B7/B5 | C8: =C7/C5 | D8: =D7/D5
A10: OPERATING EXPENSE
A11: Research & development | B11: =-'1 Drivers'!B38*'1 Drivers'!B39 | C11: =-'1 Drivers'!C38*'1 Drivers'!C39 | D11: =-'1 Drivers'!D38*'1 Drivers'!D39 | E11: 4 → 12 → 26 engineers
A12: Sales & marketing | B12: =-('1 Drivers'!B19*'1 Drivers'!B21+'1 Drivers'!B20*'1 Drivers'!B22) | C12: =-('1 Drivers'!C19*'1 Drivers'!C21+'1 Drivers'!C20*'1 Drivers'!C22) | D12: =-('1 Drivers'!D19*'1 Drivers'!D21+'1 Drivers'!D20*'1 Drivers'!D22) | E12: New logos × CAC, both segments
A13: New logos acquired | B13: ='1 Drivers'!B19+'1 Drivers'!B20 | C13: ='1 Drivers'!C19+'1 Drivers'!C20 | D13: ='1 Drivers'!D19+'1 Drivers'!D20
A14: General & administrative | B14: =-'1 Drivers'!B40 | C14: =-'1 Drivers'!C40 | D14: =-'1 Drivers'!D40
A15: Total operating expense | B15: =SUM(B11:B12)+B14 | C15: =SUM(C11:C12)+C14 | D15: =SUM(D11:D12)+D14
A17: EBITDA | B17: =B7+B15 | C17: =C7+C15 | D17: =D7+D15
A18: EBITDA margin | B18: =B17/B5 | C18: =C17/C5 | D18: =D17/D5
A19: Cumulative EBITDA | B19: =B17 | C19: =B19+C17 | D19: =C19+D17
A21: Peak cumulative burn is $5.58M. An $8.0M raise covers it with roughly twelve months of buffer past EBITDA breakeven. Sales & marketing is the largest operating line in all three years, and 73% of it is provider acquisition — which the payer channel is what makes cheap.

Sheet 5 Unit Economics
A1: CAC, LTV, and Payback — at 2028 economics
A2: LTV is stated on a 3-year horizon. The 5-year figure is shown, but we do not underwrite on it.
A4: Metric | B4: Provider group | C4: Payer | D4: Blended | E4: Note
A5: Annual revenue per account | B5: =('1 Drivers'!D14*'2 Revenue'!D7)+('1 Drivers'!D15*12) | C5: ='1 Drivers'!D16 | D5: ='2 Revenue'!D14/('1 Drivers'!D7+'1 Drivers'!D11)
A6: Gross margin applied | B6: ='3 Cost of Revenue'!D15 | C6: ='3 Cost of Revenue'!D15 | D6: ='3 Cost of Revenue'!D15
A7: Gross profit per account | B7: =B5*B6 | C7: =C5*C6 | D7: =D5*D6
A8: Annual logo churn | B8: ='1 Drivers'!D23 | C8: ='1 Drivers'!D24 | D8: =('1 Drivers'!D7*B8+'1 Drivers'!D11*C8)/('1 Drivers'!D7+'1 Drivers'!D11)
A10: Customer acquisition cost | B10: ='1 Drivers'!D21 | C10: ='1 Drivers'!D22 | D10: =-'4 P&L'!D12/'4 P&L'!D13
A12: LIFETIME VALUE
A13: Year 1 gross profit | B13: =B7 | C13: =C7 | D13: =D7
A14: Year 2 gross profit | B14: =B7*(1-B8) | C14: =C7*(1-C8) | D14: =D7*(1-D8)
A15: Year 3 gross profit | B15: =B7*(1-B8)^2 | C15: =C7*(1-C8)^2 | D15: =D7*(1-D8)^2
A16: Year 4 gross profit | B16: =B7*(1-B8)^3 | C16: =C7*(1-C8)^3 | D16: =D7*(1-D8)^3
A17: Year 5 gross profit | B17: =B7*(1-B8)^4 | C17: =C7*(1-C8)^4 | D17: =D7*(1-D8)^4
A18: LTV — 3-year | B18: =SUM(B13:B15) | C18: =SUM(C13:C15) | D18: =SUM(D13:D15)
A19: LTV — 5-year | B19: =SUM(B13:B17) | C19: =SUM(C13:C17) | D19: =SUM(D13:D17)
A21: LTV : CAC (3-year) | B21: =B18/B10 | C21: =C18/C10 | D21: =D18/D10
A22: CAC payback | B22: =B10/(B7/12) | C22: =C10/(C7/12) | D22: =D10/(D7/12)
A24: Read the payer column correctly. At 2.3× LTV:CAC and a 15-month payback, payer contracts do not pay for themselves as a standalone product, and we are not pretending otherwise. The payer contract is a distribution channel: signing one payer makes Pavo reachable by every provider group already submitting authorizations to it, which is why provider CAC falls 37% across the plan. Judged alone the payer line looks weak; judged as the thing that makes the provider line work, it is the highest-leverage spend in the model.

Sheet 6 Server & API Cost
A1: Server and API Cost — measured, not assumed
A2: Derived from timings taken against the committed code on 13 September 2026.
A4: Component | B4: Measured | C4: Unit cost | D4: Cost per auth | E4: How it was measured
A5: MEASURED PERFORMANCE
A6: Authorization decision — p50 latency | B6: 0.0886 | C6: 20 consecutive POST /api/auth/request calls
A7: Authorization decision — p95 latency | B7: 0.1133
A8: Agent-to-agent resolution | B8: 0.0447 | C8: average_resolution_seconds from /api/system/stats
A9: ZK proof generation | B9: 0.406 | C9: Groth16, 5 runs
A10: ZK proof verification | B10: 0.409
A11: Database rows written per authorization | B11: 8 | C11: 1 auth_request + 2 aria_messages + 5 audit_log
A12: Payload written per authorization (kB) | B12: 6
A14: MARGINAL COST OF ONE AUTHORIZATION
A15: Component | B15: Quantity | C15: Unit cost | D15: Cost per auth | E15: Note
A16: Compute — vCPU seconds | B16: =B6 | C16: 1.25e-05 | D16: =B16*C16 | E16: $0.045/vCPU-hour on a managed container platform
A17: Database write + 7-year retention | B17: =B12/1000000 | C17: 10.5 | D17: =B17*C17 | E17: 6 kB held 84 months at $0.125/GB/month
A18: ZK proof (20% of authorizations) | B18: =B9*0.2 | C18: 1.25e-05 | D18: =B18*C18 | E18: Short-lived Node process; only when the payer requires it
A19: Model API tokens | B19: 0 | C19: 0 | D19: 0 | E19: No inference on the authorization path — by design
A20: Load balancing, logging, observability overhead | B20: 1 | C20: 0.0005 | D20: =B20*C20 | E20: Allocated; dominates the measured components
A21: Marginal cost per authorization | D21: =SUM(D16:D20)
A22: Revenue per authorization | D22: ='1 Drivers'!D14
A23: Marginal gross margin per authorization | D23: =1-D21/D22
A25: ANNUAL INFRASTRUCTURE BUDGET vs. MARGINAL COST
A26: Authorizations processed | B26: ='2 Revenue'!B8 | C26: ='2 Revenue'!C8 | D26: ='2 Revenue'!D8
A27: Marginal cost at scale | B27: =B26*$D$21 | C27: =C26*$D$21 | D27: =D26*$D$21
A28: Budgeted cloud infrastructure | B28: ='1 Drivers'!B27 | C28: ='1 Drivers'!C27 | D28: ='1 Drivers'!D27
A29: Headroom (budget less marginal) | B29: =B28-B27 | C29: =C28-C27 | D29: =D28-D27
A31: The budget deliberately exceeds the marginal cost by a wide margin: it carries baseline capacity, staging and disaster-recovery environments, observability, and the reserved headroom an availability commitment to a payer requires. The point of this tab is not that infrastructure is cheap — it is that infrastructure is not what this business spends money on. People encoding payer criteria are (tab 3).

Sheet 7 Sensitivity
A1: Sensitivity — the assumptions that break the model
A2: Each row re-computes 2028 revenue with one driver changed. The last row changes all four.
A4: Scenario | B4: Provider groups | C4: Routed share | D4: Fee per auth | E4: Payers | F4: 2028 revenue | G4: vs. base
A5: Base case | B5: 1400 | C5: 0.5 | D5: 3 | E5: 160 | F5: =B5*('1 Drivers'!D8*'1 Drivers'!D9*52*C5)*D5+B5*'1 Drivers'!D15*12+E5*'1 Drivers'!D16 | G5: =F5/$F$5-1
A6: CMS-0057-F slips a year → payer count halves | B6: 1400 | C6: 0.5 | D6: 3 | E6: 80 | F6: =B6*('1 Drivers'!D8*'1 Drivers'!D9*52*C6)*D6+B6*'1 Drivers'!D15*12+E6*'1 Drivers'!D16 | G6: =F6/$F$5-1
A7: Routed share is 35%, not 50% | B7: 1400 | C7: 0.35 | D7: 3 | E7: 160 | F7: =B7*('1 Drivers'!D8*'1 Drivers'!D9*52*C7)*D7+B7*'1 Drivers'!D15*12+E7*'1 Drivers'!D16 | G7: =F7/$F$5-1
A8: Provider groups reach 900 average, not 1,400 | B8: 900 | C8: 0.5 | D8: 3 | E8: 160 | F8: =B8*('1 Drivers'!D8*'1 Drivers'!D9*52*C8)*D8+B8*'1 Drivers'!D15*12+E8*'1 Drivers'!D16 | G8: =F8/$F$5-1
A9: Authorization fee compresses to $2.00 | B9: 1400 | C9: 0.5 | D9: 2 | E9: 160 | F9: =B9*('1 Drivers'!D8*'1 Drivers'!D9*52*C9)*D9+B9*'1 Drivers'!D15*12+E9*'1 Drivers'!D16 | G9: =F9/$F$5-1
A10: All four together | B10: 900 | C10: 0.35 | D10: 2 | E10: 80 | F10: =B10*('1 Drivers'!D8*'1 Drivers'!D9*52*C10)*D10+B10*'1 Drivers'!D15*12+E10*'1 Drivers'!D16 | G10: =F10/$F$5-1
A12: Provider group count is the model's single greatest exposure — halving it costs more than halving the payer count and compressing price combined, because authorization fees are 72% of 2028 revenue. It is also the driver most within our control, which is why the ask in the report weights payer business development so heavily: the payer channel is what makes provider acquisition affordable at that scale.
